.flake8
ChangeLog
LICENSE
MANIFEST.in
Makefile
README.md
pyproject.toml
setup.cfg
doc/Makefile
doc/conf.py
doc/index.rst
l10n/ca.po
l10n/de.po
l10n/es.po
l10n/fr.po
l10n/messages.pot
l10n/oc.po
l10n/sv.po
l10n/uk.po
l10n/zh_Hans.po
src/openpaperwork_gtk/__init__.py
src/openpaperwork_gtk/_version.py
src/openpaperwork_gtk/colors.py
src/openpaperwork_gtk/deps.py
src/openpaperwork_gtk/gtk_init.py
src/openpaperwork_gtk/resources.py
src/openpaperwork_gtk/screenshots.py
src/openpaperwork_gtk.egg-info/PKG-INFO
src/openpaperwork_gtk.egg-info/SOURCES.txt
src/openpaperwork_gtk.egg-info/dependency_links.txt
src/openpaperwork_gtk.egg-info/requires.txt
src/openpaperwork_gtk.egg-info/top_level.txt
src/openpaperwork_gtk/bug_report/__init__.py
src/openpaperwork_gtk/bug_report/bug_report.glade
src/openpaperwork_gtk/bug_report/bug_report_http.glade
src/openpaperwork_gtk/bug_report/bug_report_method.glade
src/openpaperwork_gtk/bug_report/bug_report_zip.glade
src/openpaperwork_gtk/bug_report/http.py
src/openpaperwork_gtk/bug_report/zip.py
src/openpaperwork_gtk/busy/__init__.py
src/openpaperwork_gtk/busy/mouse.py
src/openpaperwork_gtk/dialogs/__init__.py
src/openpaperwork_gtk/dialogs/yes_no.py
src/openpaperwork_gtk/dialogs/single_entry/__init__.py
src/openpaperwork_gtk/dialogs/single_entry/single_entry.glade
src/openpaperwork_gtk/drawer/__init__.py
src/openpaperwork_gtk/drawer/pillow.py
src/openpaperwork_gtk/drawer/scan.py
src/openpaperwork_gtk/external_apps/__init__.py
src/openpaperwork_gtk/external_apps/gio.py
src/openpaperwork_gtk/fs/__init__.py
src/openpaperwork_gtk/fs/gio.py
src/openpaperwork_gtk/gesture/__init__.py
src/openpaperwork_gtk/gesture/autoscrolling.py
src/openpaperwork_gtk/l10n/__init__.py
src/openpaperwork_gtk/l10n/out/__init__.py
src/openpaperwork_gtk/l10n/out/de/__init__.py
src/openpaperwork_gtk/l10n/out/de/LC_MESSAGES/__init__.py
src/openpaperwork_gtk/l10n/out/de/LC_MESSAGES/openpaperwork_gtk.mo
src/openpaperwork_gtk/l10n/out/es/__init__.py
src/openpaperwork_gtk/l10n/out/es/LC_MESSAGES/__init__.py
src/openpaperwork_gtk/l10n/out/es/LC_MESSAGES/openpaperwork_gtk.mo
src/openpaperwork_gtk/l10n/out/fr/__init__.py
src/openpaperwork_gtk/l10n/out/fr/LC_MESSAGES/__init__.py
