Metadata-Version: 2.1
Name: openpaperwork-gtk
Version: 2.2.4
Summary: OpenPaperwork's GTK plugins
Author-email: Jerome Flesch <jflesch@openpaper.work>
License: GPL-3.0-or-later
License-File: LICENSE
Requires-Dist: openpaperwork-core
Requires-Dist: pygobject
Provides-Extra: dev
Requires-Dist: pytest; extra == "dev"
Provides-Extra: lint
Requires-Dist: flake8; extra == "lint"
